llm_hippocampus/__init__.py
llm_hippocampus/env.py
llm_hippocampus/session.py
llm_hippocampus/context/__init__.py
llm_hippocampus/context/context_manager.py
llm_hippocampus/context/context_processing.py
llm_hippocampus/context/context_retrieval.py
llm_hippocampus/core/__init__.py
llm_hippocampus/core/cached_llm.py
llm_hippocampus/core/logger.py
llm_hippocampus/core/memory.py
llm_hippocampus/core/redis.py
llm_hippocampus/core/utils.py
llm_hippocampus-0.0.5.dist-info/licenses/LICENSE
llm_hippocampus-0.0.5.dist-info/METADATA
llm_hippocampus-0.0.5.dist-info/WHEEL
llm_hippocampus-0.0.5.dist-info/top_level.txt
llm_hippocampus-0.0.5.dist-info/RECORD
