Metadata-Version: 2.4
Name: llm-hippocampus
Version: 0.0.5
Summary: LLM Hippocampus — a Context Engineering playground
Home-page: 
Author: joelz
Author-email: joelz <zhongbj_2621@163.com>
Project-URL: Repository, https://github.com/redis-developer/redis-rag-workbench.git
Project-URL: Bug Tracker, https://github.com/redis-developer/redis-rag-workbench/issues
Keywords: python,redis,langchain,openai
Classifier: Development Status :: 4 - Beta
Classifier: Intended Audience :: Developers
Classifier: Programming Language :: Python
Requires-Python: >=3.11
License-File: LICENSE
Requires-Dist: openai>=1.63.0
Requires-Dist: python-dotenv>=1.0.0
Requires-Dist: langchain>=0.3.19
Requires-Dist: tiktoken>=0.9.0
Requires-Dist: redis>=5.2.1
Requires-Dist: langchain-community>=0.3.18
Requires-Dist: langchain-huggingface>=0.1.2
Requires-Dist: langchain-openai>=0.3.6
Requires-Dist: langchain-experimental>=0.3.4
Requires-Dist: python-ulid>=2.7.0
Requires-Dist: pandas==2.2.3
Requires-Dist: hf-xet>=1.1.8
Requires-Dist: redisvl>=0.8.2
Requires-Dist: sentence-transformers>=5.1.0
Requires-Dist: langchain-redis>=0.2.3
Provides-Extra: dev
Requires-Dist: mypy<2.0.0,>=1.8.0; extra == "dev"
Requires-Dist: ruff<1.0.0,>=0.2.2; extra == "dev"
Dynamic: author
Dynamic: license-file
Dynamic: requires-python
